LICENSE
README.md
setup.py
richard_fib_py/__init__.py
richard_fib_py/version.py
richard_fib_py.egg-info/PKG-INFO
richard_fib_py.egg-info/SOURCES.txt
richard_fib_py.egg-info/dependency_links.txt
richard_fib_py.egg-info/entry_points.txt
richard_fib_py.egg-info/requires.txt
richard_fib_py.egg-info/top_level.txt
richard_fib_py/cmd/__init__.py
richard_fib_py/cmd/fib_numb.py
richard_fib_py/fib_calcs/__init__.py
richard_fib_py/fib_calcs/fib_number.py
richard_fib_py/fib_calcs/fib_numbers.py
tests/richard_fib_py/__init__.py
tests/richard_fib_py/fib_calcs/__init__.py
tests/richard_fib_py/fib_calcs/test_fib_number.py
tests/richard_fib_py/fib_calcs/test_fib_numbers.py